<?xml version='1.0' encoding='UTF-8'?>
<organe xmlns="http://schemas.assemblee-nationale.fr/referentiel" xmlns:xsi="http://www.w3.org/2001/XMLSchema-instance" xsi:type="OrganeExterne_Type">
  <uid>PO684926</uid>
  <codeType>PARPOL</codeType>
  <libelle>Parti communiste français</libelle>
  <libelleEdition>Parti communiste français</libelleEdition>
  <libelleAbrege>Parti communiste français</libelleAbrege>
  <libelleAbrev>PCF</libelleAbrev>
  <viMoDe>
    <dateDebut xsi:nil="true"/>
    <dateAgrement xsi:nil="true"/>
    <dateFin xsi:nil="true"/>
  </viMoDe>
  <organeParent xsi:nil="true"/>
  <preseance xsi:nil="true"/>
  <organePrecedentRef xsi:nil="true"/>
</organe>
