<?xml version='1.0' encoding='UTF-8'?>
<reunion xmlns="http://schemas.assemblee-nationale.fr/referentiel" xmlns:xsi="http://www.w3.org/2001/XMLSchema-instance" xsi:type="reunionCommission_type">
  <uid>RUANR5L16S2023IDC448308</uid>
  <timeStampDebut>2023-05-11T14:00:00.000+02:00</timeStampDebut>
  <lieu>
    <lieuRef>SLANPBS6550</lieuRef>
    <libelleLong>Salle 6550 – Palais Bourbon, 2ème étage</libelleLong>
  </lieu>
  <cycleDeVie>
    <etat>Confirmé</etat>
    <chrono>
      <creation>2023-05-05T00:00:00.000+02:00</creation>
      <cloture xsi:nil="true"/>
    </chrono>
  </cycleDeVie>
  <demandeur xsi:nil="true"/>
  <organeReuniRef>PO821469</organeReuniRef>
  <participants>
    <participantsInternes/>
    <personnesAuditionnees/>
  </participants>
  <visioConference>false</visioConference>
  <sessionRef xsi:nil="true"/>
  <ouverturePresse>false</ouverturePresse>
  <captationVideo>false</captationVideo>
  <ODJ>
    <convocationODJ>
      <item>Table ronde d’agences de presse</item>
      <item>- Agence France presse (AFP) – M. Fabrice Fries, président-directeur général</item>
      <item>- Syndicat des Agences de Presse Audiovisuelles / Fédération française des agences de Presse (SATEV/FFAP) – M. Christian Gerin, président, et Mme Florence Braka, directrice générale </item>
    </convocationODJ>
    <resumeODJ>
      <item>table ronde d’agences de presse ;</item>
      <item>- agence France presse (AFP) – M. Fabrice Fries, président-directeur général ;</item>
      <item>- syndicat des Agences de Presse Audiovisuelles / Fédération française des agences de Presse (SATEV/FFAP) – M. Christian Gerin, président, et Mme Florence Braka, directrice générale.</item>
    </resumeODJ>
    <pointsODJ/>
  </ODJ>
  <compteRenduRef xsi:nil="true"/>
  <formatReunion>Ordinaire</formatReunion>
  <infosReunionsInternationale>
    <estReunionInternationale>false</estReunionInternationale>
    <listePays xsi:nil="true"/>
  </infosReunionsInternationale>
</reunion>
