<?xml version='1.0' encoding='UTF-8'?>
<dossierParlementaire xmlns="http://schemas.assemblee-nationale.fr/referentiel" xmlns:xsi="http://www.w3.org/2001/XMLSchema-instance" xsi:type="DossierLegislatif_Type">
  <uid>DLR5L16N45971</uid>
  <legislature>16</legislature>
  <titreDossier>
    <titre>Approbation de l’accord entre le Gouvernement de la République française et la Cour pénale internationale sur l’exécution des peines prononcées par la Cour</titre>
    <titreChemin>accord_cour_penale_internationale</titreChemin>
    <senatChemin>http://www.senat.fr/dossier-legislatif/pjl22-196.html</senatChemin>
  </titreDossier>
  <procedureParlementaire>
    <code>6</code>
    <libelle>Projet de ratification des traités et conventions</libelle>
  </procedureParlementaire>
  <initiateur>
    <acteurs>
      <acteur>
        <acteurRef>PA717161</acteurRef>
        <mandatRef>PM791583</mandatRef>
      </acteur>
      <acteur>
        <acteurRef>PA717161</acteurRef>
        <mandatRef>PM791583</mandatRef>
      </acteur>
      <acteur>
        <acteurRef>PA717161</acteurRef>
        <mandatRef>PM791583</mandatRef>
      </acteur>
      <acteur>
        <acteurRef>PA717161</acteurRef>
        <mandatRef>PM791583</mandatRef>
      </acteur>
      <acteur>
        <acteurRef>PA717161</acteurRef>
        <mandatRef>PM791583</mandatRef>
      </acteur>
      <acteur>
        <acteurRef>PA717161</acteurRef>
        <mandatRef>PM791583</mandatRef>
      </acteur>
      <acteur>
        <acteurRef>PA717161</acteurRef>
        <mandatRef>PM791583</mandatRef>
      </acteur>
      <acteur>
        <acteurRef>PA717161</acteurRef>
        <mandatRef>PM791583</mandatRef>
      </acteur>
      <acteur>
        <acteurRef>PA717161</acteurRef>
        <mandatRef>PM791583</mandatRef>
      </acteur>
      <acteur>
        <acteurRef>PA717161</acteurRef>
        <mandatRef>PM791583</mandatRef>
      </acteur>
      <acteur>
        <acteurRef>PA717161</acteurRef>
        <mandatRef>PM791583</mandatRef>
      </acteur>
      <acteur>
        <acteurRef>PA717161</acteurRef>
        <mandatRef>PM791583</mandatRef>
      </acteur>
      <acteur>
        <acteurRef>PA717161</acteurRef>
        <mandatRef>PM791583</mandatRef>
      </acteur>
      <acteur>
        <acteurRef>PA717161</acteurRef>
        <mandatRef>PM791583</mandatRef>
      </acteur>
      <acteur>
        <acteurRef>PA717161</acteurRef>
        <mandatRef>PM791583</mandatRef>
      </acteur>
      <acteur>
        <acteurRef>PA717161</acteurRef>
        <mandatRef>PM791583</mandatRef>
      </acteur>
      <acteur>
        <acteurRef>PA717161</acteurRef>
        <mandatRef>PM791583</mandatRef>
      </acteur>
      <acteur>
        <acteurRef>PA717161</acteurRef>
        <mandatRef>PM791583</mandatRef>
      </acteur>
      <acteur>
        <acteurRef>PA717161</acteurRef>
        <mandatRef>PM791583</mandatRef>
      </acteur>
      <acteur>
        <acteurRef>PA717161</acteurRef>
        <mandatRef>PM791583</mandatRef>
      </acteur>
      <acteur>
        <acteurRef>PA717161</acteurRef>
        <mandatRef>PM791583</mandatRef>
      </acteur>
      <acteur>
        <acteurRef>PA717161</acteurRef>
        <mandatRef>PM791583</mandatRef>
      </acteur>
      <acteur>
        <acteurRef>PA717161</acteurRef>
        <mandatRef>PM791583</mandatRef>
      </acteur>
      <acteur>
        <acteurRef>PA717161</acteurRef>
        <mandatRef>PM791583</mandatRef>
      </acteur>
      <acteur>
        <acteurRef>PA717161</acteurRef>
        <mandatRef>PM791583</mandatRef>
      </acteur>
      <acteur>
        <acteurRef>PA312976</acteurRef>
        <mandatRef>PM791676</mandatRef>
      </acteur>
      <acteur>
        <acteurRef>PA312976</acteurRef>
        <mandatRef>PM791676</mandatRef>
      </acteur>
      <acteur>
        <acteurRef>PA312976</acteurRef>
        <mandatRef>PM791676</mandatRef>
      </acteur>
      <acteur>
        <acteurRef>PA312976</acteurRef>
        <mandatRef>PM791676</mandatRef>
      </acteur>
    </acteurs>
  </initiateur>
  <actesLegislatifs>
    <acteLegislatif xsi:type="Etape_Type">
      <uid>L16-AN1-45971</uid>
      <codeActe>AN1</codeActe>
      <libelleActe>
        <nomCanonique>1ère lecture (1ère assemblée saisie)</nomCanonique>
        <libelleCourt>1ère lecture</libelleCourt>
      </libelleActe>
      <organeRef>PO791932</organeRef>
      <dateActe xsi:nil="true"/>
      <actesLegislatifs>
        <acteLegislatif xsi:type="DepotInitiative_Type">
          <uid>L16-VD208395DI</uid>
          <codeActe>AN1-DEPOT</codeActe>
          <libelleActe>
            <nomCanonique>1er dépôt d'une initiative.</nomCanonique>
            <libelleCourt>1er dépôt d'une initiative.</libelleCourt>
          </libelleActe>
          <organeRef>PO791932</organeRef>
          <dateActe>2022-07-13T00:00:00.000+02:00</dateActe>
          <actesLegislatifs xsi:nil="true"/>
          <texteAssocie>PRJLANR5L16B0145</texteAssocie>
        </acteLegislatif>
        <acteLegislatif xsi:type="EtudeImpact_Type">
          <uid>L16-VD208395ETI</uid>
          <codeActe>AN1-ETI</codeActe>
          <libelleActe>
            <nomCanonique>Etude d'impact</nomCanonique>
            <libelleCourt>Etude d'impact</libelleCourt>
          </libelleActe>
          <organeRef>PO791932</organeRef>
          <dateActe>2022-07-13T00:00:00.000+02:00</dateActe>
          <actesLegislatifs xsi:nil="true"/>
          <contributionInternaute>
            <dateOuverture>2022-07-14+02:00</dateOuverture>
            <dateFermeture>2022-12-08+01:00</dateFermeture>
          </contributionInternaute>
          <texteAssocie>ETDIANR5L16B0145</texteAssocie>
        </acteLegislatif>
        <acteLegislatif xsi:type="DepotAccordInternational_Type">
          <uid>L16-VD208395ACIN</uid>
          <codeActe>AN1-ACIN</codeActe>
          <libelleActe>
            <nomCanonique>Accord international</nomCanonique>
            <libelleCourt>Accord international</libelleCourt>
          </libelleActe>
          <organeRef>PO791932</organeRef>
          <dateActe>2022-07-13T00:00:00.000+02:00</dateActe>
          <actesLegislatifs xsi:nil="true"/>
          <texteAssocie>ACINANR5L16B0145</texteAssocie>
        </acteLegislatif>
        <acteLegislatif xsi:type="ProcedureAccelere_Type">
          <uid>L16-VD211330</uid>
          <codeActe>AN1-PROCACC</codeActe>
          <libelleActe>
            <nomCanonique>Le gouvernement déclare l'urgence / engage la procédure accélérée</nomCanonique>
            <libelleCourt>Le gouvernement déclare l'urgence / engage la procédure accélérée</libelleCourt>
          </libelleActe>
          <organeRef>PO791579</organeRef>
          <dateActe>2022-07-13T00:00:00.000+02:00</dateActe>
          <actesLegislatifs xsi:nil="true"/>
        </acteLegislatif>
        <acteLegislatif xsi:type="Etape_Type">
          <uid>L16-AN1-COM-45971</uid>
          <codeActe>AN1-COM</codeActe>
          <libelleActe>
            <nomCanonique>Travaux des commissions</nomCanonique>
            <libelleCourt>Travaux des commissions</libelleCourt>
          </libelleActe>
          <organeRef>PO791932</organeRef>
          <dateActe xsi:nil="true"/>
          <actesLegislatifs>
            <acteLegislatif xsi:type="Etape_Type">
              <uid>L16-VD208396CF</uid>
              <codeActe>AN1-COM-FOND</codeActe>
              <libelleActe>
                <nomCanonique>Travaux de la commission saisie au fond</nomCanonique>
                <libelleCourt>Travaux de la commission saisie au fond</libelleCourt>
              </libelleActe>
              <organeRef>PO59047</organeRef>
              <dateActe xsi:nil="true"/>
              <actesLegislatifs>
                <acteLegislatif xsi:type="SaisieComFond_Type">
                  <uid>L16-VD208396CFS</uid>
                  <codeActe>AN1-COM-FOND-SAISIE</codeActe>
                  <libelleActe>
                    <nomCanonique>Renvoi en commission au fond</nomCanonique>
                    <libelleCourt>Renvoi en commission au fond</libelleCourt>
                  </libelleActe>
                  <organeRef>PO59047</organeRef>
                  <dateActe>2022-07-13T00:00:00.000+02:00</dateActe>
                  <actesLegislatifs xsi:nil="true"/>
                </acteLegislatif>
                <acteLegislatif xsi:type="NominRapporteurs_Type">
                  <uid>L16-VD209378</uid>
                  <codeActe>AN1-COM-FOND-NOMIN</codeActe>
                  <libelleActe>
                    <nomCanonique>Nomination de rapporteur</nomCanonique>
                    <libelleCourt>Nomination de rapporteur</libelleCourt>
                  </libelleActe>
                  <organeRef>PO59047</organeRef>
                  <dateActe>2022-10-05T00:00:00.000+02:00</dateActe>
                  <actesLegislatifs xsi:nil="true"/>
                  <rapporteurs>
                    <rapporteur>
                      <acteurRef>PA795326</acteurRef>
                      <typeRapporteur>rapporteur</typeRapporteur>
                    </rapporteur>
                  </rapporteurs>
                  <reunion xsi:nil="true"/>
                </acteLegislatif>
                <acteLegislatif xsi:type="DiscussionCommission_Type">
                  <uid>L16-VD209748R31809</uid>
                  <codeActe>AN1-COM-FOND-REUNION</codeActe>
                  <libelleActe>
                    <nomCanonique>Réunion de commission</nomCanonique>
                    <libelleCourt>Réunion de commission</libelleCourt>
                  </libelleActe>
                  <organeRef>PO59047</organeRef>
                  <dateActe>2022-10-05T09:00:00.000+02:00</dateActe>
                  <actesLegislatifs xsi:nil="true"/>
                  <reunionRef>RUANR5L16S2023IDC445614</reunionRef>
                  <odjRef>RUANR5L16S2023IDC445614PT31809</odjRef>
                </acteLegislatif>
                <acteLegislatif xsi:type="DiscussionCommission_Type">
                  <uid>L16-VD209748R31806</uid>
                  <codeActe>AN1-COM-FOND-REUNION</codeActe>
                  <libelleActe>
                    <nomCanonique>Réunion de commission</nomCanonique>
                    <libelleCourt>Réunion de commission</libelleCourt>
                  </libelleActe>
                  <organeRef>PO59047</organeRef>
                  <dateActe>2022-11-23T09:00:00.000+01:00</dateActe>
                  <actesLegislatifs xsi:nil="true"/>
                  <reunionRef>RUANR5L16S2023IDC445985</reunionRef>
                  <odjRef>RUANR5L16S2023IDC445985PT31806</odjRef>
                </acteLegislatif>
                <acteLegislatif xsi:type="DepotRapport_Type">
                  <uid>L16-VD210297</uid>
                  <codeActe>AN1-COM-FOND-RAPPORT</codeActe>
                  <libelleActe>
                    <nomCanonique>Dépôt de rapport</nomCanonique>
                    <libelleCourt>Dépôt de rapport</libelleCourt>
                  </libelleActe>
                  <organeRef>PO59047</organeRef>
                  <dateActe>2022-11-23T00:00:00.000+01:00</dateActe>
                  <actesLegislatifs xsi:nil="true"/>
                  <texteAssocie>RAPPANR5L16B0511</texteAssocie>
                  <texteAdopte xsi:nil="true"/>
                </acteLegislatif>
              </actesLegislatifs>
            </acteLegislatif>
          </actesLegislatifs>
        </acteLegislatif>
        <acteLegislatif xsi:type="Etape_Type">
          <uid>L16-AN1-DEBATS-45971</uid>
          <codeActe>AN1-DEBATS</codeActe>
          <libelleActe>
            <nomCanonique>Discussion en séance publique</nomCanonique>
            <libelleCourt>Discussion en séance publique</libelleCourt>
          </libelleActe>
          <organeRef>PO791932</organeRef>
          <dateActe xsi:nil="true"/>
          <actesLegislatifs>
            <acteLegislatif xsi:type="DiscussionSeancePublique_Type">
              <uid>L16-VD210071S44759</uid>
              <codeActe>AN1-DEBATS-SEANCE</codeActe>
              <libelleActe>
                <nomCanonique>Discussion en séance publique</nomCanonique>
                <libelleCourt>Discussion en séance publique</libelleCourt>
              </libelleActe>
              <organeRef>PO791932</organeRef>
              <dateActe>2022-12-08T00:00:00.000+01:00</dateActe>
              <actesLegislatifs xsi:nil="true"/>
              <reunionRef>RUANR5L16S2023IDS26603</reunionRef>
              <odjRef>RUANR5L16S2023IDS26603PT44759</odjRef>
            </acteLegislatif>
            <acteLegislatif xsi:type="Decision_Type">
              <uid>L16-VD210637DEC</uid>
              <codeActe>AN1-DEBATS-DEC</codeActe>
              <libelleActe>
                <nomCanonique>Décision</nomCanonique>
                <libelleCourt>Décision</libelleCourt>
              </libelleActe>
              <organeRef>PO791932</organeRef>
              <dateActe>2022-12-08T00:00:00.000+01:00</dateActe>
              <actesLegislatifs xsi:nil="true"/>
              <statutConclusion>
                <fam_code>TSORTF01</fam_code>
                <libelle>adopté</libelle>
              </statutConclusion>
              <reunionRef>RUANR5L16S2023IDS26603</reunionRef>
              <voteRefs xsi:nil="true"/>
              <textesAssocies>
                <texteAssocie>
                  <typeTexte>BTA</typeTexte>
                  <refTexteAssocie>PRJLANR5L16BTA0049</refTexteAssocie>
                </texteAssocie>
              </textesAssocies>
            </acteLegislatif>
          </actesLegislatifs>
        </acteLegislatif>
      </actesLegislatifs>
    </acteLegislatif>
    <acteLegislatif xsi:type="Etape_Type">
      <uid>L16-SN1-45971</uid>
      <codeActe>SN1</codeActe>
      <libelleActe>
        <nomCanonique>1ère lecture (2ème assemblée saisie)</nomCanonique>
        <libelleCourt>1ère lecture</libelleCourt>
      </libelleActe>
      <organeRef>PO78718</organeRef>
      <dateActe xsi:nil="true"/>
      <actesLegislatifs>
        <acteLegislatif xsi:type="DepotInitiativeNavette_Type">
          <uid>L16-VD210649DIN</uid>
          <codeActe>SN1-DEPOT</codeActe>
          <libelleActe>
            <nomCanonique>Dépôt d'une initiative en navette</nomCanonique>
            <libelleCourt>Dépôt d'une initiative en navette</libelleCourt>
          </libelleActe>
          <organeRef>PO78718</organeRef>
          <dateActe>2022-12-08T00:00:00.000+01:00</dateActe>
          <actesLegislatifs xsi:nil="true"/>
          <texteAssocie>PRJLSNR5S399B0196</texteAssocie>
          <provenance>PO791932</provenance>
          <depotInitialLectureDefinitiveRef xsi:nil="true"/>
        </acteLegislatif>
        <acteLegislatif xsi:type="Etape_Type">
          <uid>L16-SN1-COM-45971</uid>
          <codeActe>SN1-COM</codeActe>
          <libelleActe>
            <nomCanonique>Travaux des commissions</nomCanonique>
            <libelleCourt>Travaux des commissions</libelleCourt>
          </libelleActe>
          <organeRef>PO78718</organeRef>
          <dateActe xsi:nil="true"/>
          <actesLegislatifs>
            <acteLegislatif xsi:type="Etape_Type">
              <uid>L16-VD210650CF</uid>
              <codeActe>SN1-COM-FOND</codeActe>
              <libelleActe>
                <nomCanonique>Travaux de la commission saisie au fond</nomCanonique>
                <libelleCourt>Travaux de la commission saisie au fond</libelleCourt>
              </libelleActe>
              <organeRef>PO211491</organeRef>
              <dateActe xsi:nil="true"/>
              <actesLegislatifs>
                <acteLegislatif xsi:type="SaisieComFond_Type">
                  <uid>L16-VD210650CFS</uid>
                  <codeActe>SN1-COM-FOND-SAISIE</codeActe>
                  <libelleActe>
                    <nomCanonique>Renvoi en commission au fond</nomCanonique>
                    <libelleCourt>Renvoi en commission au fond</libelleCourt>
                  </libelleActe>
                  <organeRef>PO211491</organeRef>
                  <dateActe>2022-12-08T00:00:00.000+01:00</dateActe>
                  <actesLegislatifs xsi:nil="true"/>
                </acteLegislatif>
                <acteLegislatif xsi:type="NominRapporteurs_Type">
                  <uid>L16-VD211613</uid>
                  <codeActe>SN1-COM-FOND-NOMIN</codeActe>
                  <libelleActe>
                    <nomCanonique>Nomination de rapporteur</nomCanonique>
                    <libelleCourt>Nomination de rapporteur</libelleCourt>
                  </libelleActe>
                  <organeRef>PO211491</organeRef>
                  <dateActe xsi:nil="true"/>
                  <actesLegislatifs xsi:nil="true"/>
                  <rapporteurs>
                    <rapporteur>
                      <acteurRef>PA720634</acteurRef>
                      <typeRapporteur>rapporteur</typeRapporteur>
                    </rapporteur>
                  </rapporteurs>
                  <reunion xsi:nil="true"/>
                </acteLegislatif>
                <acteLegislatif xsi:type="DepotRapport_Type">
                  <uid>L16-VD211614</uid>
                  <codeActe>SN1-COM-FOND-RAPPORT</codeActe>
                  <libelleActe>
                    <nomCanonique>Dépôt de rapport</nomCanonique>
                    <libelleCourt>Dépôt de rapport</libelleCourt>
                  </libelleActe>
                  <organeRef>PO211491</organeRef>
                  <dateActe>2023-02-08T00:00:00.000+01:00</dateActe>
                  <actesLegislatifs xsi:nil="true"/>
                  <texteAssocie>RAPPSNR5S399B0332</texteAssocie>
                  <texteAdopte>PRJLSNR5S399BTC0333</texteAdopte>
                </acteLegislatif>
              </actesLegislatifs>
            </acteLegislatif>
          </actesLegislatifs>
        </acteLegislatif>
        <acteLegislatif xsi:type="Etape_Type">
          <uid>L16-SN1-DEBATS-45971</uid>
          <codeActe>SN1-DEBATS</codeActe>
          <libelleActe>
            <nomCanonique>Discussion en séance publique</nomCanonique>
            <libelleCourt>Discussion en séance publique</libelleCourt>
          </libelleActe>
          <organeRef>PO78718</organeRef>
          <dateActe xsi:nil="true"/>
          <actesLegislatifs>
            <acteLegislatif xsi:type="Decision_Type">
              <uid>L16-VD211791DEC</uid>
              <codeActe>SN1-DEBATS-DEC</codeActe>
              <libelleActe>
                <nomCanonique>Décision</nomCanonique>
                <libelleCourt>Décision</libelleCourt>
              </libelleActe>
              <organeRef>PO78718</organeRef>
              <dateActe>2023-02-16T00:00:00.000+01:00</dateActe>
              <actesLegislatifs xsi:nil="true"/>
              <statutConclusion>
                <fam_code>TSORTF05</fam_code>
                <libelle>modifié</libelle>
              </statutConclusion>
              <reunionRef xsi:nil="true"/>
              <voteRefs xsi:nil="true"/>
              <textesAssocies>
                <texteAssocie>
                  <typeTexte>BTA</typeTexte>
                  <refTexteAssocie>PRJLSNR5S399BTA0059</refTexteAssocie>
                </texteAssocie>
              </textesAssocies>
            </acteLegislatif>
          </actesLegislatifs>
        </acteLegislatif>
      </actesLegislatifs>
    </acteLegislatif>
    <acteLegislatif xsi:type="Etape_Type">
      <uid>L16-PROM-45971</uid>
      <codeActe>PROM</codeActe>
      <libelleActe>
        <nomCanonique>Promulgation de la loi</nomCanonique>
        <libelleCourt>Promulgation de la loi</libelleCourt>
      </libelleActe>
      <organeRef>PO717136</organeRef>
      <dateActe xsi:nil="true"/>
      <actesLegislatifs>
        <acteLegislatif xsi:type="Promulgation_Type">
          <uid>L16-VD211880PL</uid>
          <codeActe>PROM-PUB</codeActe>
          <libelleActe>
            <nomCanonique>Promulgation d'une loi</nomCanonique>
            <libelleCourt>Promulgation d'une loi</libelleCourt>
          </libelleActe>
          <organeRef>PO717136</organeRef>
          <dateActe>2023-02-21T00:00:00.000+01:00</dateActe>
          <actesLegislatifs xsi:nil="true"/>
          <infoJO>
            <typeJO>JO_LOI_DECRET</typeJO>
            <dateJO>2023-02-22+01:00</dateJO>
            <pageJO xsi:nil="true"/>
            <numJO>45</numJO>
            <urlLegifrance>http://www.legifrance.gouv.fr/WAspad/UnTexteDeJorf?numjo=EAEJ2214409L</urlLegifrance>
            <referenceNOR>EAEJ2214409L</referenceNOR>
          </infoJO>
          <urlEcheancierLoi xsi:nil="true"/>
          <codeLoi>2023-115</codeLoi>
          <titreLoi>autorisant l’approbation de l’accord entre le Gouvernement de la République française et la Cour pénale internationale sur l’exécution des peines prononcées par la Cour</titreLoi>
        </acteLegislatif>
      </actesLegislatifs>
    </acteLegislatif>
  </actesLegislatifs>
  <fusionDossier/>
</dossierParlementaire>
